MANIFEST.in
README.rest
setup.py
unitstorm.py
tests/test_mtc.py
tests/fixtures/insert1.sql
tests/fixtures/insert2.sql
unitstorm.egg-info/PKG-INFO
unitstorm.egg-info/SOURCES.txt
unitstorm.egg-info/dependency_links.txt
unitstorm.egg-info/requires.txt
unitstorm.egg-info/top_level.txt
unitstorm.egg-info/zip-safe