Metadata-Version: 1.0
Name: unitstorm
Version: 0.1.1
Summary: Unit testing microframework for Storm ORM models
Home-page: http://pypi.python.org/pypi/unitstorm
Author: Vsevolod Balashov
Author-email: vsevolod@balashov.name
License: LGPL 2.1
Keywords: unit test testing unittest unittesting storm orm db dbms rdbms sql fixture fixtures postgres postgresql mysql sqlite
Platform: UNKNOWN
Classifier: Development Status :: 4 - Beta
Classifier: Environment :: Console
Classifier: Intended Audience :: Developers
Classifier: License :: OSI Approved :: GNU Library or Lesser General Public License (LGPL)
Classifier: Natural Language :: Russian
Classifier: Operating System :: OS Independent
Classifier: Programming Language :: Python
Classifier: Topic :: Database
Classifier: Topic :: Software Development :: Testing
